{
  "measurements": [
    {
      "date": "2025-01-29",
      "kappa": 438.9,
      "lambda": 5.7
    },
    {
      "date": "2025-02-05",
      "kappa": 487.7,
      "lambda": 6.5
    },
    {
      "date": "2025-02-27",
      "kappa": 212.9,
      "lambda": 2.9
    },
    {
      "date": "2025-03-13",
      "kappa": 238.2,
      "lambda": 3.0
    },
    {
      "date": "2025-03-20",
      "kappa": 194.7,
      "lambda": 2.5
    },
    {
      "date": "2025-03-27",
      "kappa": 186.3,
      "lambda": 1.9
    },
    {
      "date": "2025-04-03",
      "kappa": 182.2,
      "lambda": 1.8
    },
    {
      "date": "2025-04-08",
      "kappa": 176.0,
      "lambda": 2.3
    },
    {
      "date": "2025-04-10",
      "kappa": 176.8,
      "lambda": 2.1
    },
    {
      "date": "2025-04-17",
      "kappa": 134.4,
      "lambda": 1.8
    },
    {
      "date": "2025-04-24",
      "kappa": 104.8,
      "lambda": 1.9
    },
    {
      "date": "2025-05-01",
      "kappa": 84.3,
      "lambda": 1.4
    },
    {
      "date": "2025-05-08",
      "kappa": 65.7,
      "lambda": 1.4
    },
    {
      "date": "2025-05-15",
      "kappa": 57.3,
      "lambda": 1.4
    },
    {
      "date": "2025-05-22",
      "kappa": 49.6,
      "lambda": 1.4
    },
    {
      "date": "2025-05-29",
      "kappa": 41.3,
      "lambda": 1.4
    },
    {
      "date": "2025-06-05",
      "kappa": 40.1,
      "lambda": 1.4
    },
    {
      "date": "2025-06-12",
      "kappa": 34.5,
      "lambda": 1.4
    },
    {
      "date": "2025-06-19",
      "kappa": 26.9,
      "lambda": 1.4
    },
    {
      "date": "2025-06-26",
      "kappa": 25.1,
      "lambda": 1.4
    },
    {
      "date": "2025-07-03",
      "kappa": 23.2,
      "lambda": 1.4
    },
    {
      "date": "2025-07-10",
      "kappa": 20.3,
      "lambda": 1.4
    },
    {
      "date": "2025-07-17",
      "kappa": 19.5,
      "lambda": 1.4
    },
    {
      "date": "2025-07-25",
      "kappa": 17.2,
      "lambda": 1.4
    }
  ],
  "settings": {
    "split_date": "2025-04-10",
    "projection_end_date": "2025-10-01",
    "vgpr_threshold": 40.0,
    "cr_threshold": 19.4
  }
}
